pont/__init__.py
pont/__main__.py
pont/buffer.py
pont/flow.py
pont/proxy.py
pont/settings.py
pont/cli/__init__.py
pont/cli/daemon.py
pont/cli/demo.py
pont/cli/init.py
pont/database/__init__.py
pont/database/database.py
pont/database/filters.py
pont/database/query.py
pont/database/query_error.py
pont/protocols/__init__.py
pont/protocols/http.py
pont/protocols/protocol.py
pont/protocols/ssl.py
pont/renderer/__init__.py
pont/renderer/mimetype.py
pont/tests/__init__.py
pont/tests/test_flow.py
pont/tests/test_renderer.py
pont/tests/test_settings.py
pont/tests/database/test_database.py
pont/tests/database/test_filters.py
pont/tests/database/test_query.py
pont/tests/protocols/__init__.py
pont/tests/protocols/conftest.py
pont/tests/protocols/helpers.py
pont/tests/protocols/mock.py
pont/tests/protocols/test_http.py
pont/tests/protocols/test_ssl.py
pont/tests/ui/routes/conftest.py
pont/tests/ui/routes/test_config.py
pont/tests/ui/routes/test_flow.py
pont/tests/ui/routes/test_flows.py
pont/tests/ui/routes/test_index.py
pont/ui/__init__.py
pont/ui/filters.py
pont/ui/helpers.py
pont/ui/routes/__init__.py
pont/ui/routes/config.py
pont/ui/routes/flow.py
pont/ui/routes/flows.py
pont/ui/routes/index.py
pont/ui/static/favicon.png
pont/ui/static/htmx.min.js
pont/ui/static/logo.png
pont/ui/static/style.css
pont/ui/static/tabler/LICENSE
pont/ui/static/tabler/tabler.css
pont/ui/static/tabler/tabler.js
pont/ui/static/tabler/update_tabler.sh
pont/ui/templates/config.html.j2
pont/ui/templates/index.html.j2
pont/ui/templates/layout.html.j2
pont/ui/templates/components/error.html.j2
pont/ui/templates/components/flows.html.j2
pont/ui/templates/flow/body.html.j2
pont/ui/templates/flow/flow.html.j2
pont/ui/templates/flow/headers.html.j2
pont/ui/templates/flow/summary.html.j2
pont/ui/templates/renderer/mimetype.html.j2
pont/ui/templates/renderer/unknown.html.j2
pont-0.0.7.dist-info/METADATA
pont-0.0.7.dist-info/WHEEL
pont-0.0.7.dist-info/entry_points.txt
pont-0.0.7.dist-info/licenses/AUTHORS.md
pont-0.0.7.dist-info/licenses/LICENSE
pont-0.0.7.dist-info/RECORD
